changelog_machine/ChangelogGenerator.py
changelog_machine/Config.py
changelog_machine/EntryGenerator.py
changelog_machine/NewChangelog.py
changelog_machine/VersionUtil.py
changelog_machine/__init__.py
changelog_machine/__main__.py
changelog_machine/changelogGenerator.py
changelog_machine/entryGenerator.py
changelog_machine/versions/VersionUtil.py
changelog_machine/versions/__init__.py
changelog_machine-0.20.0.data/scripts/changelog-machine
tests/__init__.py
tests/changelog_machine/__init__.py
tests/changelog_machine/test_NewChangelog.py
tests/changelog_machine/test_VersionUtil.py
tests/changelog_machine/integration_tests/__init__.py
tests/changelog_machine/integration_tests/no_changelog_file/__init__.py
tests/changelog_machine/integration_tests/no_changelog_file/test_integration.py
tests/src/__init__.py
tests/src/test_NewChangelog.py
tests/src/test_VersionUtil.py
tests/src/integration_tests/__init__.py
tests/src/integration_tests/no_changelog_file/__init__.py
tests/src/integration_tests/no_changelog_file/test_integration.py
changelog_machine-0.20.0.dist-info/LICENSE
changelog_machine-0.20.0.dist-info/METADATA
changelog_machine-0.20.0.dist-info/WHEEL
changelog_machine-0.20.0.dist-info/top_level.txt
changelog_machine-0.20.0.dist-info/RECORD
