Metadata-Version: 2.1
Name: changelog-machine
Version: 0.20.0
Summary: A tool to generate changelogs integrated in a pull/merge request workflow
Home-page: https://github.com/greenhalos/changelog-machine
Author: Ben Antony
Author-email: antony@greenhalos.lu
License: UNKNOWN
Platform: UNKNOWN
Classifier: Programming Language :: Python :: 3
Classifier: Operating System :: OS Independent
Requires-Python: >=3.6
Requires-Dist: PyYAML (>=5.3.1)
